django_authz/__init__.py
django_authz/admin.py
django_authz/apps.py
django_authz/authz.py
django_authz/backend.py
django_authz/base.py
django_authz/const.py
django_authz/decorators.py
django_authz/middleware.py
django_authz/mixins.py
django_authz/models.py
django_authz/registry.py
django_authz/roles.py
django_authz/tests.py
django_authz/utils.py
django_authz/views.py
django_authz-1.0.12.dist-info/DESCRIPTION.rst
django_authz-1.0.12.dist-info/METADATA
django_authz-1.0.12.dist-info/RECORD
django_authz-1.0.12.dist-info/SOURCES.txt.py
django_authz-1.0.12.dist-info/WHEEL
django_authz-1.0.12.dist-info/dependency_links.txt.py
django_authz-1.0.12.dist-info/metadata.json
django_authz-1.0.12.dist-info/top_level.txt
django_authz-1.0.12.dist-info/top_level.txt.py
