Metadata-Version: 2.0
Name: django-authz
Version: 1.0.12
Summary: Yet another approach to authorization in django
Home-page: https://bitbucket.org/dleonarski/django-authz.git
Author: Dariusz Leonarski
Author-email: dariusz@leonarski.pl
License: MIT
Keywords: django,authorization
Platform: UNKNOWN
Classifier: Development Status :: 3 - Alpha
Classifier: Intended Audience :: Developers
Classifier: Topic :: Software Development :: Build Tools
Classifier: License :: OSI Approved :: MIT License
Classifier: Programming Language :: Python :: 3.4
